exactypes/__init__.py
exactypes/array.py
exactypes/exceptions.py
exactypes/types.py
exactypes/cdataobject/__init__.py
exactypes/cdataobject/datafield.py
exactypes/cdataobject/refsolver.py
exactypes/cfuncs/__init__.py
exactypes/cfuncs/argtypes.py
exactypes/cfuncs/restype.py
exactypes-0.4.0.dist-info/LICENSE
exactypes-0.4.0.dist-info/METADATA
exactypes-0.4.0.dist-info/WHEEL
exactypes-0.4.0.dist-info/top_level.txt
exactypes-0.4.0.dist-info/RECORD
