Metadata-Version: 2.2
Name: exactypes
Version: 0.4.0
Summary: Helps creating typed ctypes-based python library
Author-email: HivertMoZara <worldmozara@163.com>
License: MIT
Project-URL: Homepage, https://github.com/NCBM/exactypes
Project-URL: Repository, https://github.com/NCBM/exactypes
Requires-Python: >=3.9
License-File: LICENSE
Requires-Dist: typing_extensions<5,>=4
